{"current":{"logo":"shopify:\/\/shop_images\/Group_481767.png","logo_width":210,"media_logo_width":120,"favicon":"shopify:\/\/shop_images\/Frame_13.png","swatchColors":"Black:#000000\nWhite:#f5f5f5\nBlue:#005eff\nRed:#c9002c\nPink:#ffd5e6\nBrown:#a2896b\nOlive:#808000\nPurple:#dac6ef\nGrey:#e2e2e7\nBeige:#d8c7af\nRed&green:#c9002c#008000\nBlack&orange&olive:#000000#FFA500#808000","font_weight":"900","text_style":"capitalize","theme_mainheading_fontsize":34,"theme_maindescription_fontsize":14,"bg_color":"#ffffff","border_color":"#e5e5e5","page_title_text_color":"#333333","theme_subheading_color":"#90b200","theme_main_color":"#90b200","theme_text_hover_color":"#90b200","theme_dots":"#90b200","theme_dots_active":"#333333","button_bg":"#90b200","button_hr_bg":"#333333","button_hr_text":"#ffffff","q_button_border":"#333333","q_button_bg":"#ffffff","q_button_color":"#333333","q_button_hr_bg":"#90b200","input_bg_color":"#f9f6f1","input_text_color":"#333333","input_border_color":"#f9f6f1","type_header_font":"nunito_n8","heading_scale":100,"type_body_font":"roboto_n4","body_scale":100,"page_width":1620,"spacing_grid_horizontal":30,"spacing_grid_vertical":30,"show_cookie":true,"box_bg":"#f9f6f1","box_hr_text":"#ff7800","cookie_url":"shopify:\/\/pages\/privacy-policy","ena_popup_news":false,"image1":"shopify:\/\/shop_images\/newslatter.webp","subheading_newslatter":"#ff7800","endbtn_text":"#ff7800","endbtn_hr_text":"#333333","color_breadcrumbs_bg":"#f9f6f1","color_breadcrumbs_active":"#666666","color_breadcrumbs_hover":"#ff7800","animations_reveal_on_scroll":true,"buttons_radius":10,"inputs_radius":10,"card_style":"card","card_image_padding":0,"card_text_alignment":"left","card_corner_radius":10,"p_button_position":"up_position","p_image_ratio":"adapt","p_image_shape":"default","p_show_vendor":false,"p_enable_quick_add":true,"p_quantity_enable":false,"product_card_main_color":"#f9f6f1","card-border-color":"#e5e5e5","card_button_bg":"#90b200","card_button_text":"#ffffff","card_button_hr_bg":"#333333","card_button_hr_text":"#ffffff","card_product_vendor_color":"#333333","card_product_title_color":"#333333","card_product_title_hr_color":"#90b200","card_product_regular_price_color":"#90b200","collection_card_style":"card","collection_card_image_padding":0,"collection_card_text_alignment":"left","collection_card_main_color":"#f9f6f1","collection_card_corner_radius":10,"blog_card_style":"standard","blog_card_image_padding":0,"blog_card_text_alignment":"left","blog_card_main_color":"#f9f6f1","card_date_color":"#ff7800","card_author_name_color":"#ff7800","card_hr_heading_color":"#ff7800","card_button_color":"#333333","card_button_hr_color":"#ff7800","blog_card_corner_radius":10,"media_radius":10,"popup_corner_radius":10,"badge_position":"top left","badge_corner_radius":6,"badge_bg_color":"#333333","social_facebook_link":"#","social_instagram_link":"#","social_youtube_link":"","social_tiktok_link":"","social_twitter_link":"#","social_snapchat_link":"","social_pinterest_link":"#","social_tumblr_link":"","social_vimeo_link":"","quick_search":"grocery, food, vegetable, fruits","predictive_search_enabled":true,"predictive_search_show_vendor":true,"predictive_search_show_price":true,"currency_code_enabled":true,"cart_type":"drawer","show_vendor":false,"show_cart_note":true,"cart_drawer_collection":"","amount_setup":"200000","freeshipping_text":"#333333","freeshipping_bg":"#f9f6f1","freeshipping_active_bg":"#ff7800","section_bg":"#ffffff","text_color":"#333333","style_breadcrumb":"style_1","tag_attachment":true,"checkout_sidebar_background_color":"#f9f6f1","checkout_error_color":"#b72323","heading-img":"shopify:\/\/shop_images\/L13-seperator.png","enable-fack-product":true,"best_product_collection":"arrival","name_purchare":"Name Purchare","animations_hover_elements":"default","inputs_border_thickness":1,"inputs_border_opacity":55,"inputs_shadow_opacity":0,"inputs_shadow_horizontal_offset":0,"inputs_shadow_vertical_offset":4,"inputs_shadow_blur":5,"card_border_thickness":0,"card_border_opacity":10,"card_shadow_opacity":0,"card_shadow_horizontal_offset":0,"card_shadow_vertical_offset":4,"card_shadow_blur":5,"collection_card_border_thickness":0,"collection_card_border_opacity":10,"collection_card_shadow_opacity":0,"collection_card_shadow_horizontal_offset":0,"collection_card_shadow_vertical_offset":4,"collection_card_shadow_blur":5,"blog_card_border_thickness":0,"blog_card_border_opacity":10,"blog_card_shadow_opacity":0,"blog_card_shadow_horizontal_offset":0,"blog_card_shadow_vertical_offset":4,"blog_card_shadow_blur":5,"text_boxes_border_thickness":0,"text_boxes_border_opacity":10,"text_boxes_radius":0,"text_boxes_shadow_opacity":0,"text_boxes_shadow_horizontal_offset":0,"text_boxes_shadow_vertical_offset":4,"text_boxes_shadow_blur":5,"media_border_thickness":1,"media_border_opacity":5,"media_shadow_opacity":0,"media_shadow_horizontal_offset":0,"media_shadow_vertical_offset":4,"media_shadow_blur":5,"popup_border_thickness":1,"popup_border_opacity":10,"popup_shadow_opacity":5,"popup_shadow_horizontal_offset":0,"popup_shadow_vertical_offset":4,"popup_shadow_blur":5,"drawer_border_thickness":1,"drawer_border_opacity":10,"drawer_shadow_opacity":0,"drawer_shadow_horizontal_offset":0,"drawer_shadow_vertical_offset":4,"drawer_shadow_blur":5,"brand_headline":"","brand_description":"<p><\/p>","brand_image_width":100,"spacing_sections":0,"buttons_border_thickness":1,"buttons_border_opacity":100,"buttons_shadow_opacity":0,"buttons_shadow_horizontal_offset":0,"buttons_shadow_vertical_offset":4,"buttons_shadow_blur":5,"variant_pills_border_thickness":1,"variant_pills_border_opacity":55,"variant_pills_radius":40,"variant_pills_shadow_opacity":0,"variant_pills_shadow_horizontal_offset":0,"variant_pills_shadow_vertical_offset":4,"variant_pills_shadow_blur":5,"cart_color_scheme":"accent-2","card_color_scheme":"background-1","sale_badge_color_scheme":"accent-2","sold_out_badge_color_scheme":"inverse","blog_card_color_scheme":"background-2","collection_card_color_scheme":"background-1","sections":{"main-password-footer":{"type":"main-password-footer","settings":{}},"mobile-bottom-menu":{"type":"mobile-bottom-menu","blocks":{"cart_8bmKyt":{"type":"cart","settings":{}},"wishlist_778jRC":{"type":"wishlist","settings":{}},"home_WeUckz":{"type":"home","settings":{}},"account_ate8V9":{"type":"account","settings":{}},"compare_eTpijx":{"type":"compare","settings":{}}},"block_order":["cart_8bmKyt","wishlist_778jRC","home_WeUckz","account_ate8V9","compare_eTpijx"],"settings":{"menu_style":"menu_square","background-color":"#ffffff","icon-color":"#333333"}},"side-widget":{"type":"side-widget","settings":{"widget-enable":true,"position":"right","show_wishlist":true,"show_compare":true,"bg_color":"#ffffff","icon_color":"#333333","bg_hr_color":"#90b200","icon_hr_color":"#ffffff","border_color":"#333333"}},"fake-product-purchase":{"type":"fake-product-purchase","blocks":{"image_Uyz3XU":{"type":"image","settings":{"product":"aashirvaad-rice-dosa-instant","address":"USA","time":"5 minute ago"}},"image_PwJa8y":{"type":"image","settings":{"product":"bingo-original-style-salt-sprinkled","address":"USA","time":"5 minute ago"}}},"block_order":["image_Uyz3XU","image_PwJa8y"],"settings":{"enable-fake-popup":true,"popup-position":"left","section_bg":"#ffffff"}}},"content_for_index":[],"blocks":{"15909290956780699707":{"type":"shopify:\/\/apps\/mw-product-bundles\/blocks\/app-embed-block\/5bcb1a6d-53b5-4d9c-b4f9-19f6620da62b","disabled":false,"settings":{"theme_text_primary_color":"#1A1C1D","theme_text_secondary_color":"#7C8488","theme_primary_button_background_color":"#1A1C1D","theme_primary_button_text_color":"#FFFFFF","theme_input_control_text_color":"#1A1C1D","theme_input_control_background_color":"#FFFFFF","theme_stars_background_color":"#46b200","theme_positive_text_color":"#00AB2D","theme_negative_text_color":"#E51C00","theme_divider_background_color":"#EBEBEB","theme_plus_icon_color":"#1A1C1D","theme_volume_title_color":"#7c8488","theme_volume_discount_bage_text_color":"#420000","theme_volume_discount_bage_background_color":"#fdd8d8","theme_volume_selected_state_color":"#1773b0","theme_volume_selected_state_background_color":"#f4f8fb","theme_bogo_discount_bage_background_color":"#fdd8d8","theme_bogo_discount_bage_text_color":"#420000","volume_layout_style":"vertical","theme_font_family":"inter_n4","theme_heading_font_size":20,"theme_body_font_size":16,"disable_upsell_crossell_popup":false,"custom_liquid":""}}},"color_schemes":{"background-1":{"settings":{"background":"#ffffff","background_gradient":"","text":"#121212","button":"#121212","button_label":"#ffffff","secondary_button_label":"#121212","shadow":"#121212"}},"background-2":{"settings":{"background":"#f3f3f3","background_gradient":"","text":"#121212","button":"#121212","button_label":"#f3f3f3","secondary_button_label":"#121212","shadow":"#121212"}},"inverse":{"settings":{"background":"#242833","background_gradient":"","text":"#ffffff","button":"#ffffff","button_label":"#000000","secondary_button_label":"#ffffff","shadow":"#121212"}},"accent-1":{"settings":{"background":"#121212","background_gradient":"","text":"#ffffff","button":"#ffffff","button_label":"#121212","secondary_button_label":"#ffffff","shadow":"#121212"}},"accent-2":{"settings":{"background":"#334fb4","background_gradient":"","text":"#ffffff","button":"#ffffff","button_label":"#334fb4","secondary_button_label":"#ffffff","shadow":"#121212"}},"scheme-5021415c-c79d-4894-a364-ef057e6d3bb9":{"settings":{"background":"#ffffff","background_gradient":"","text":"#121212","button":"#121212","button_label":"#ffffff","secondary_button_label":"#121212","shadow":"#121212"}}}},"presets":{"Default":{"logo_width":90,"color_schemes":{"background-1":{"settings":{"background":"#FFFFFF","background_gradient":"","text":"#121212","button":"#121212","button_label":"#FFFFFF","secondary_button_label":"#121212","shadow":"#121212"}},"background-2":{"settings":{"background":"#F3F3F3","background_gradient":"","text":"#121212","button":"#121212","button_label":"#F3F3F3","secondary_button_label":"#121212","shadow":"#121212"}},"inverse":{"settings":{"background":"#242833","background_gradient":"","text":"#FFFFFF","button":"#FFFFFF","button_label":"#000000","secondary_button_label":"#FFFFFF","shadow":"#121212"}},"accent-1":{"settings":{"background":"#121212","background_gradient":"","text":"#FFFFFF","button":"#FFFFFF","button_label":"#121212","secondary_button_label":"#FFFFFF","shadow":"#121212"}},"accent-2":{"settings":{"background":"#334FB4","background_gradient":"","text":"#FFFFFF","button":"#FFFFFF","button_label":"#334FB4","secondary_button_label":"#FFFFFF","shadow":"#121212"}}},"type_header_font":"assistant_n4","heading_scale":100,"type_body_font":"assistant_n4","body_scale":100,"page_width":1200,"spacing_sections":0,"spacing_grid_horizontal":8,"spacing_grid_vertical":8,"animations_reveal_on_scroll":true,"animations_hover_elements":"none","buttons_border_thickness":1,"buttons_border_opacity":100,"buttons_radius":0,"buttons_shadow_opacity":0,"buttons_shadow_horizontal_offset":0,"buttons_shadow_vertical_offset":4,"buttons_shadow_blur":5,"variant_pills_border_thickness":1,"variant_pills_border_opacity":55,"variant_pills_radius":40,"variant_pills_shadow_opacity":0,"variant_pills_shadow_horizontal_offset":0,"variant_pills_shadow_vertical_offset":4,"variant_pills_shadow_blur":5,"inputs_border_thickness":1,"inputs_border_opacity":55,"inputs_radius":0,"inputs_shadow_opacity":0,"inputs_shadow_horizontal_offset":0,"inputs_shadow_vertical_offset":4,"inputs_shadow_blur":5,"card_style":"standard","card_image_padding":0,"card_text_alignment":"left","card_color_scheme":"background-2","card_border_thickness":0,"card_border_opacity":10,"card_corner_radius":0,"card_shadow_opacity":0,"card_shadow_horizontal_offset":0,"card_shadow_vertical_offset":4,"card_shadow_blur":5,"collection_card_style":"standard","collection_card_image_padding":0,"collection_card_text_alignment":"left","collection_card_color_scheme":"background-2","collection_card_border_thickness":0,"collection_card_border_opacity":10,"collection_card_corner_radius":0,"collection_card_shadow_opacity":0,"collection_card_shadow_horizontal_offset":0,"collection_card_shadow_vertical_offset":4,"collection_card_shadow_blur":5,"blog_card_style":"standard","blog_card_image_padding":0,"blog_card_text_alignment":"left","blog_card_color_scheme":"background-2","blog_card_border_thickness":0,"blog_card_border_opacity":10,"blog_card_corner_radius":0,"blog_card_shadow_opacity":0,"blog_card_shadow_horizontal_offset":0,"blog_card_shadow_vertical_offset":4,"blog_card_shadow_blur":5,"text_boxes_border_thickness":0,"text_boxes_border_opacity":10,"text_boxes_radius":0,"text_boxes_shadow_opacity":0,"text_boxes_shadow_horizontal_offset":0,"text_boxes_shadow_vertical_offset":4,"text_boxes_shadow_blur":5,"media_border_thickness":1,"media_border_opacity":5,"media_radius":0,"media_shadow_opacity":0,"media_shadow_horizontal_offset":0,"media_shadow_vertical_offset":4,"media_shadow_blur":5,"popup_border_thickness":1,"popup_border_opacity":10,"popup_corner_radius":0,"popup_shadow_opacity":5,"popup_shadow_horizontal_offset":0,"popup_shadow_vertical_offset":4,"popup_shadow_blur":5,"drawer_border_thickness":1,"drawer_border_opacity":10,"drawer_shadow_opacity":0,"drawer_shadow_horizontal_offset":0,"drawer_shadow_vertical_offset":4,"drawer_shadow_blur":5,"badge_position":"bottom left","badge_corner_radius":40,"sale_badge_color_scheme":"accent-2","sold_out_badge_color_scheme":"inverse","brand_headline":"","brand_description":"<p><\/p>","brand_image_width":100,"social_twitter_link":"","social_facebook_link":"","social_pinterest_link":"","social_instagram_link":"","social_tiktok_link":"","social_tumblr_link":"","social_snapchat_link":"","social_youtube_link":"","social_vimeo_link":"","predictive_search_enabled":true,"predictive_search_show_vendor":false,"predictive_search_show_price":false,"currency_code_enabled":true,"cart_type":"notification","show_vendor":false,"show_cart_note":false,"cart_drawer_collection":"","cart_color_scheme":"background-1","sections":{"main-password-footer":{"type":"main-password-footer","settings":{}}}}}}